{
	"name": "batch_trunc_Dimensions",
	"properties": {
		"activities": [
			{
				"name": "Truncate DimBranch",
				"type": "Script",
				"dependsOn": [],
				"policy": {
					"timeout": "7.00:00:00",
					"retry": 0,
					"retryIntervalInSeconds": 30,
					"secureOutput": false,
					"secureInput": false
				},
				"userProperties": [],
				"linkedServiceName": {
					"referenceName": "RDC",
					"type": "LinkedServiceReference"
				},
				"typeProperties": {
					"scripts": [
						{
							"type": "Query",
							"text": "TRUNCATE TABLE EDW.DIM_BRANCH"
						}
					]
				}
			},
			{
				"name": "Truncate DimCallResult",
				"type": "Script",
				"dependsOn": [
					{
						"activity": "Truncate DimBranch",
						"dependencyConditions": [
							"Succeeded"
						]
					}
				],
				"policy": {
					"timeout": "7.00:00:00",
					"retry": 0,
					"retryIntervalInSeconds": 30,
					"secureOutput": false,
					"secureInput": false
				},
				"userProperties": [],
				"linkedServiceName": {
					"referenceName": "RDC",
					"type": "LinkedServiceReference"
				},
				"typeProperties": {
					"scripts": [
						{
							"type": "Query",
							"text": "TRUNCATE TABLE EDW.DIM_CALL_RESULT"
						}
					]
				}
			},
			{
				"name": "Truncate DimCallType",
				"type": "Script",
				"dependsOn": [
					{
						"activity": "Truncate DimCallResult",
						"dependencyConditions": [
							"Succeeded"
						]
					}
				],
				"policy": {
					"timeout": "7.00:00:00",
					"retry": 0,
					"retryIntervalInSeconds": 30,
					"secureOutput": false,
					"secureInput": false
				},
				"userProperties": [],
				"linkedServiceName": {
					"referenceName": "RDC",
					"type": "LinkedServiceReference"
				},
				"typeProperties": {
					"scripts": [
						{
							"type": "Query",
							"text": "TRUNCATE TABLE EDW.DIM_CALL_TYPE"
						}
					]
				}
			},
			{
				"name": "Truncate DimCustomer",
				"type": "Script",
				"dependsOn": [],
				"policy": {
					"timeout": "7.00:00:00",
					"retry": 0,
					"retryIntervalInSeconds": 30,
					"secureOutput": false,
					"secureInput": false
				},
				"userProperties": [],
				"linkedServiceName": {
					"referenceName": "RDC",
					"type": "LinkedServiceReference"
				},
				"typeProperties": {
					"scripts": [
						{
							"type": "Query",
							"text": "TRUNCATE TABLE EDW.DIM_CUSTOMER"
						}
					]
				}
			},
			{
				"name": "Truncate DimDisposition",
				"type": "Script",
				"dependsOn": [],
				"policy": {
					"timeout": "7.00:00:00",
					"retry": 0,
					"retryIntervalInSeconds": 30,
					"secureOutput": false,
					"secureInput": false
				},
				"userProperties": [],
				"linkedServiceName": {
					"referenceName": "RDC",
					"type": "LinkedServiceReference"
				},
				"typeProperties": {
					"scripts": [
						{
							"type": "Query",
							"text": "TRUNCATE TABLE EDW.DIM_DISPOSITION"
						}
					]
				}
			},
			{
				"name": "Truncate DimDispositionCategory",
				"type": "Script",
				"dependsOn": [
					{
						"activity": "Truncate DimDisposition",
						"dependencyConditions": [
							"Succeeded"
						]
					}
				],
				"policy": {
					"timeout": "7.00:00:00",
					"retry": 0,
					"retryIntervalInSeconds": 30,
					"secureOutput": false,
					"secureInput": false
				},
				"userProperties": [],
				"linkedServiceName": {
					"referenceName": "RDC",
					"type": "LinkedServiceReference"
				},
				"typeProperties": {
					"scripts": [
						{
							"type": "Query",
							"text": "TRUNCATE TABLE EDW.DIM_DISPOSITION_CATEGORY"
						}
					]
				}
			},
			{
				"name": "Truncate DimEmployee",
				"type": "Script",
				"dependsOn": [
					{
						"activity": "Truncate DimDispositionCategory",
						"dependencyConditions": [
							"Succeeded"
						]
					}
				],
				"policy": {
					"timeout": "7.00:00:00",
					"retry": 0,
					"retryIntervalInSeconds": 30,
					"secureOutput": false,
					"secureInput": false
				},
				"userProperties": [],
				"linkedServiceName": {
					"referenceName": "RDC",
					"type": "LinkedServiceReference"
				},
				"typeProperties": {
					"scripts": [
						{
							"type": "Query",
							"text": "TRUNCATE TABLE EDW.DIM_EMPLOYEE"
						}
					]
				}
			},
			{
				"name": "Truncate DimFinanceCompany",
				"type": "Script",
				"dependsOn": [
					{
						"activity": "Truncate DimCustomer",
						"dependencyConditions": [
							"Succeeded"
						]
					}
				],
				"policy": {
					"timeout": "7.00:00:00",
					"retry": 0,
					"retryIntervalInSeconds": 30,
					"secureOutput": false,
					"secureInput": false
				},
				"userProperties": [],
				"linkedServiceName": {
					"referenceName": "RDC",
					"type": "LinkedServiceReference"
				},
				"typeProperties": {
					"scripts": [
						{
							"type": "Query",
							"text": "TRUNCATE TABLE EDW.DIM_FINANCE_COMPANY"
						}
					]
				}
			},
			{
				"name": "Truncate DimFinanceSource",
				"type": "Script",
				"dependsOn": [],
				"policy": {
					"timeout": "7.00:00:00",
					"retry": 0,
					"retryIntervalInSeconds": 30,
					"secureOutput": false,
					"secureInput": false
				},
				"userProperties": [],
				"linkedServiceName": {
					"referenceName": "RDC",
					"type": "LinkedServiceReference"
				},
				"typeProperties": {
					"scripts": [
						{
							"type": "Query",
							"text": "TRUNCATE TABLE EDW.DIM_FINANCE_SOURCE"
						}
					]
				}
			},
			{
				"name": "Truncate DimHoldReason",
				"type": "Script",
				"dependsOn": [
					{
						"activity": "Truncate DimFinanceSource",
						"dependencyConditions": [
							"Succeeded"
						]
					}
				],
				"policy": {
					"timeout": "7.00:00:00",
					"retry": 0,
					"retryIntervalInSeconds": 30,
					"secureOutput": false,
					"secureInput": false
				},
				"userProperties": [],
				"linkedServiceName": {
					"referenceName": "RDC",
					"type": "LinkedServiceReference"
				},
				"typeProperties": {
					"scripts": [
						{
							"type": "Query",
							"text": "TRUNCATE TABLE EDW.DIM_HOLD_REASON"
						}
					]
				}
			},
			{
				"name": "Truncate DimInstaller",
				"type": "Script",
				"dependsOn": [
					{
						"activity": "Truncate DimHoldReason",
						"dependencyConditions": [
							"Succeeded"
						]
					}
				],
				"policy": {
					"timeout": "7.00:00:00",
					"retry": 0,
					"retryIntervalInSeconds": 30,
					"secureOutput": false,
					"secureInput": false
				},
				"userProperties": [],
				"linkedServiceName": {
					"referenceName": "RDC",
					"type": "LinkedServiceReference"
				},
				"typeProperties": {
					"scripts": [
						{
							"type": "Query",
							"text": "TRUNCATE TABLE EDW.DIM_INSTALLER"
						}
					]
				}
			},
			{
				"name": "Truncate DimJobStatus",
				"type": "Script",
				"dependsOn": [
					{
						"activity": "Truncate DimFinanceCompany",
						"dependencyConditions": [
							"Succeeded"
						]
					}
				],
				"policy": {
					"timeout": "7.00:00:00",
					"retry": 0,
					"retryIntervalInSeconds": 30,
					"secureOutput": false,
					"secureInput": false
				},
				"userProperties": [],
				"linkedServiceName": {
					"referenceName": "RDC",
					"type": "LinkedServiceReference"
				},
				"typeProperties": {
					"scripts": [
						{
							"type": "Query",
							"text": "TRUNCATE TABLE EDW.DIM_JOB_STATUS"
						}
					]
				}
			},
			{
				"name": "Truncate DimLeadSource",
				"type": "Script",
				"dependsOn": [],
				"policy": {
					"timeout": "7.00:00:00",
					"retry": 0,
					"retryIntervalInSeconds": 30,
					"secureOutput": false,
					"secureInput": false
				},
				"userProperties": [],
				"linkedServiceName": {
					"referenceName": "RDC",
					"type": "LinkedServiceReference"
				},
				"typeProperties": {
					"scripts": [
						{
							"type": "Query",
							"text": "TRUNCATE TABLE EDW.DIM_LEAD_SOURCE"
						}
					]
				}
			},
			{
				"name": "Truncate DimLeadSourceGroup",
				"type": "Script",
				"dependsOn": [
					{
						"activity": "Truncate DimLeadSource",
						"dependencyConditions": [
							"Succeeded"
						]
					}
				],
				"policy": {
					"timeout": "7.00:00:00",
					"retry": 0,
					"retryIntervalInSeconds": 30,
					"secureOutput": false,
					"secureInput": false
				},
				"userProperties": [],
				"linkedServiceName": {
					"referenceName": "RDC",
					"type": "LinkedServiceReference"
				},
				"typeProperties": {
					"scripts": [
						{
							"type": "Query",
							"text": "TRUNCATE TABLE EDW.DIM_LEAD_SOURCE_GROUP"
						}
					]
				}
			},
			{
				"name": "Truncate DimLeadSubSource",
				"type": "Script",
				"dependsOn": [
					{
						"activity": "Truncate DimLeadSourceGroup",
						"dependencyConditions": [
							"Succeeded"
						]
					}
				],
				"policy": {
					"timeout": "7.00:00:00",
					"retry": 0,
					"retryIntervalInSeconds": 30,
					"secureOutput": false,
					"secureInput": false
				},
				"userProperties": [],
				"linkedServiceName": {
					"referenceName": "RDC",
					"type": "LinkedServiceReference"
				},
				"typeProperties": {
					"scripts": [
						{
							"type": "Query",
							"text": "TRUNCATE TABLE EDW.DIM_LEAD_SUB_SOURCE"
						}
					]
				}
			},
			{
				"name": "Truncate DimMilestoneDateType",
				"type": "Script",
				"dependsOn": [],
				"policy": {
					"timeout": "7.00:00:00",
					"retry": 0,
					"retryIntervalInSeconds": 30,
					"secureOutput": false,
					"secureInput": false
				},
				"userProperties": [],
				"linkedServiceName": {
					"referenceName": "RDC",
					"type": "LinkedServiceReference"
				},
				"typeProperties": {
					"scripts": [
						{
							"type": "Query",
							"text": "TRUNCATE TABLE EDW.DIM_MILESTONE_DATE_TYPE"
						}
					]
				}
			},
			{
				"name": "Truncate DimPaymentMethod",
				"type": "Script",
				"dependsOn": [],
				"policy": {
					"timeout": "7.00:00:00",
					"retry": 0,
					"retryIntervalInSeconds": 30,
					"secureOutput": false,
					"secureInput": false
				},
				"userProperties": [],
				"linkedServiceName": {
					"referenceName": "RDC",
					"type": "LinkedServiceReference"
				},
				"typeProperties": {
					"scripts": [
						{
							"type": "Query",
							"text": "TRUNCATE TABLE EDW.DIM_PAYMENT_METHOD"
						}
					]
				}
			},
			{
				"name": "Truncate DimPaymentType",
				"type": "Script",
				"dependsOn": [
					{
						"activity": "Truncate DimPaymentMethod",
						"dependencyConditions": [
							"Succeeded"
						]
					}
				],
				"policy": {
					"timeout": "7.00:00:00",
					"retry": 0,
					"retryIntervalInSeconds": 30,
					"secureOutput": false,
					"secureInput": false
				},
				"userProperties": [],
				"linkedServiceName": {
					"referenceName": "RDC",
					"type": "LinkedServiceReference"
				},
				"typeProperties": {
					"scripts": [
						{
							"type": "Query",
							"text": "TRUNCATE TABLE EDW.DIM_PAYMENT_TYPE"
						}
					]
				}
			},
			{
				"name": "Truncate DimProduct",
				"type": "Script",
				"dependsOn": [
					{
						"activity": "Truncate DimPaymentType",
						"dependencyConditions": [
							"Succeeded"
						]
					}
				],
				"policy": {
					"timeout": "7.00:00:00",
					"retry": 0,
					"retryIntervalInSeconds": 30,
					"secureOutput": false,
					"secureInput": false
				},
				"userProperties": [],
				"linkedServiceName": {
					"referenceName": "RDC",
					"type": "LinkedServiceReference"
				},
				"typeProperties": {
					"scripts": [
						{
							"type": "Query",
							"text": "TRUNCATE TABLE EDW.DIM_PRODUCT"
						}
					]
				}
			},
			{
				"name": "Truncate DimProductGroup",
				"type": "Script",
				"dependsOn": [
					{
						"activity": "Truncate DimMilestoneDateType",
						"dependencyConditions": [
							"Succeeded"
						]
					}
				],
				"policy": {
					"timeout": "7.00:00:00",
					"retry": 0,
					"retryIntervalInSeconds": 30,
					"secureOutput": false,
					"secureInput": false
				},
				"userProperties": [],
				"linkedServiceName": {
					"referenceName": "RDC",
					"type": "LinkedServiceReference"
				},
				"typeProperties": {
					"scripts": [
						{
							"type": "Query",
							"text": "TRUNCATE TABLE EDW.DIM_PRODUCT_GROUP"
						}
					]
				}
			},
			{
				"name": "Truncate DimProductionBranch",
				"type": "Script",
				"dependsOn": [],
				"policy": {
					"timeout": "7.00:00:00",
					"retry": 0,
					"retryIntervalInSeconds": 30,
					"secureOutput": false,
					"secureInput": false
				},
				"userProperties": [],
				"linkedServiceName": {
					"referenceName": "RDC",
					"type": "LinkedServiceReference"
				},
				"typeProperties": {
					"scripts": [
						{
							"type": "Query",
							"text": "TRUNCATE TABLE EDW.DIM_PRODUCTION_BRANCH"
						}
					]
				}
			},
			{
				"name": "Truncate DimRank",
				"type": "Script",
				"dependsOn": [
					{
						"activity": "Truncate DimProductionBranch",
						"dependencyConditions": [
							"Succeeded"
						]
					}
				],
				"policy": {
					"timeout": "7.00:00:00",
					"retry": 0,
					"retryIntervalInSeconds": 30,
					"secureOutput": false,
					"secureInput": false
				},
				"userProperties": [],
				"linkedServiceName": {
					"referenceName": "RDC",
					"type": "LinkedServiceReference"
				},
				"typeProperties": {
					"scripts": [
						{
							"type": "Query",
							"text": "TRUNCATE TABLE EDW.DIM_RANK"
						}
					]
				}
			},
			{
				"name": "Truncate DimSalesDistrict",
				"type": "Script",
				"dependsOn": [
					{
						"activity": "Truncate DimRank",
						"dependencyConditions": [
							"Succeeded"
						]
					}
				],
				"policy": {
					"timeout": "7.00:00:00",
					"retry": 0,
					"retryIntervalInSeconds": 30,
					"secureOutput": false,
					"secureInput": false
				},
				"userProperties": [],
				"linkedServiceName": {
					"referenceName": "RDC",
					"type": "LinkedServiceReference"
				},
				"typeProperties": {
					"scripts": [
						{
							"type": "Query",
							"text": "TRUNCATE TABLE EDW.DIM_SALES_DISTRICT"
						}
					]
				}
			},
			{
				"name": "Truncate DimServiceCategory",
				"type": "Script",
				"dependsOn": [
					{
						"activity": "Truncate DimProductGroup",
						"dependencyConditions": [
							"Succeeded"
						]
					}
				],
				"policy": {
					"timeout": "7.00:00:00",
					"retry": 0,
					"retryIntervalInSeconds": 30,
					"secureOutput": false,
					"secureInput": false
				},
				"userProperties": [],
				"linkedServiceName": {
					"referenceName": "RDC",
					"type": "LinkedServiceReference"
				},
				"typeProperties": {
					"scripts": [
						{
							"type": "Query",
							"text": "TRUNCATE TABLE EDW.DIM_SERVICE_CATEGORY"
						}
					]
				}
			},
			{
				"name": "Truncate DimServiceStatus",
				"type": "Script",
				"dependsOn": [],
				"policy": {
					"timeout": "7.00:00:00",
					"retry": 0,
					"retryIntervalInSeconds": 30,
					"secureOutput": false,
					"secureInput": false
				},
				"userProperties": [],
				"linkedServiceName": {
					"referenceName": "RDC",
					"type": "LinkedServiceReference"
				},
				"typeProperties": {
					"scripts": [
						{
							"type": "Query",
							"text": "TRUNCATE TABLE EDW.DIM_SERVICE_STATUS"
						}
					]
				}
			},
			{
				"name": "Truncate DimCommissionPaymentType",
				"type": "Script",
				"dependsOn": [
					{
						"activity": "Truncate DimServiceStatus",
						"dependencyConditions": [
							"Succeeded"
						]
					}
				],
				"policy": {
					"timeout": "7.00:00:00",
					"retry": 0,
					"retryIntervalInSeconds": 30,
					"secureOutput": false,
					"secureInput": false
				},
				"userProperties": [],
				"linkedServiceName": {
					"referenceName": "RDC",
					"type": "LinkedServiceReference"
				},
				"typeProperties": {
					"scripts": [
						{
							"type": "Query",
							"text": "TRUNCATE TABLE EDW.DIM_COMMISSION_PAYMENT_TYPE"
						}
					]
				}
			},
			{
				"name": "Truncate DimHOAStatus",
				"type": "Script",
				"dependsOn": [
					{
						"activity": "Truncate DimCommissionPaymentType",
						"dependencyConditions": [
							"Succeeded"
						]
					}
				],
				"policy": {
					"timeout": "7.00:00:00",
					"retry": 0,
					"retryIntervalInSeconds": 30,
					"secureOutput": false,
					"secureInput": false
				},
				"userProperties": [],
				"linkedServiceName": {
					"referenceName": "RDC",
					"type": "LinkedServiceReference"
				},
				"typeProperties": {
					"scripts": [
						{
							"type": "Query",
							"text": "TRUNCATE TABLE EDW.DIM_HOA_STATUS"
						}
					]
				}
			},
			{
				"name": "Truncate DimHomeOwnersAssociation",
				"type": "Script",
				"dependsOn": [
					{
						"activity": "Truncate DimPunchList",
						"dependencyConditions": [
							"Succeeded"
						]
					}
				],
				"policy": {
					"timeout": "7.00:00:00",
					"retry": 0,
					"retryIntervalInSeconds": 30,
					"secureOutput": false,
					"secureInput": false
				},
				"userProperties": [],
				"linkedServiceName": {
					"referenceName": "RDC",
					"type": "LinkedServiceReference"
				},
				"typeProperties": {
					"scripts": [
						{
							"type": "Query",
							"text": "TRUNCATE TABLE EDW.DIM_HOMEOWNERS_ASSOCIATION"
						}
					]
				}
			},
			{
				"name": "Truncate DimJobChangeOrderType",
				"type": "Script",
				"dependsOn": [
					{
						"activity": "Truncate DimHomeOwnersAssociation",
						"dependencyConditions": [
							"Succeeded"
						]
					}
				],
				"policy": {
					"timeout": "7.00:00:00",
					"retry": 0,
					"retryIntervalInSeconds": 30,
					"secureOutput": false,
					"secureInput": false
				},
				"userProperties": [],
				"linkedServiceName": {
					"referenceName": "RDC",
					"type": "LinkedServiceReference"
				},
				"typeProperties": {
					"scripts": [
						{
							"type": "Query",
							"text": "TRUNCATE TABLE EDW.DIM_JOB_CHANGE_ORDER_TYPE"
						}
					]
				}
			},
			{
				"name": "Truncate DimJobCostCategory",
				"type": "Script",
				"dependsOn": [
					{
						"activity": "Truncate DimJobChangeOrderType",
						"dependencyConditions": [
							"Succeeded"
						]
					}
				],
				"policy": {
					"timeout": "7.00:00:00",
					"retry": 0,
					"retryIntervalInSeconds": 30,
					"secureOutput": false,
					"secureInput": false
				},
				"userProperties": [],
				"linkedServiceName": {
					"referenceName": "RDC",
					"type": "LinkedServiceReference"
				},
				"typeProperties": {
					"scripts": [
						{
							"type": "Query",
							"text": "TRUNCATE TABLE EDW.DIM_JOB_COST_CATEGORY"
						}
					]
				}
			},
			{
				"name": "Truncate DimMaterial",
				"type": "Script",
				"dependsOn": [],
				"policy": {
					"timeout": "7.00:00:00",
					"retry": 0,
					"retryIntervalInSeconds": 30,
					"secureOutput": false,
					"secureInput": false
				},
				"userProperties": [],
				"linkedServiceName": {
					"referenceName": "RDC",
					"type": "LinkedServiceReference"
				},
				"typeProperties": {
					"scripts": [
						{
							"type": "Query",
							"text": "TRUNCATE TABLE EDW.DIM_MATERIAL"
						}
					]
				}
			},
			{
				"name": "Truncate DimJobPermitStatus",
				"type": "Script",
				"dependsOn": [
					{
						"activity": "Truncate DimMaterial",
						"dependencyConditions": [
							"Succeeded"
						]
					}
				],
				"policy": {
					"timeout": "7.00:00:00",
					"retry": 0,
					"retryIntervalInSeconds": 30,
					"secureOutput": false,
					"secureInput": false
				},
				"userProperties": [],
				"linkedServiceName": {
					"referenceName": "RDC",
					"type": "LinkedServiceReference"
				},
				"typeProperties": {
					"scripts": [
						{
							"type": "Query",
							"text": "TRUNCATE TABLE EDW.DIM_JOB_PERMIT_STATUS"
						}
					]
				}
			},
			{
				"name": "Truncate DimJobPermitType",
				"type": "Script",
				"dependsOn": [
					{
						"activity": "Truncate DimJobPermitStatus",
						"dependencyConditions": [
							"Succeeded"
						]
					}
				],
				"policy": {
					"timeout": "7.00:00:00",
					"retry": 0,
					"retryIntervalInSeconds": 30,
					"secureOutput": false,
					"secureInput": false
				},
				"userProperties": [],
				"linkedServiceName": {
					"referenceName": "RDC",
					"type": "LinkedServiceReference"
				},
				"typeProperties": {
					"scripts": [
						{
							"type": "Query",
							"text": "TRUNCATE TABLE EDW.DIM_JOB_PERMIT_TYPE"
						}
					]
				}
			},
			{
				"name": "Truncate DimBranchZip",
				"type": "Script",
				"dependsOn": [],
				"policy": {
					"timeout": "7.00:00:00",
					"retry": 0,
					"retryIntervalInSeconds": 30,
					"secureOutput": false,
					"secureInput": false
				},
				"userProperties": [],
				"linkedServiceName": {
					"referenceName": "RDC",
					"type": "LinkedServiceReference"
				},
				"typeProperties": {
					"scripts": [
						{
							"type": "Query",
							"text": "TRUNCATE TABLE EDW.DIM_BRANCH_ZIP"
						}
					]
				}
			},
			{
				"name": "Truncate DimJobStatusCategory",
				"type": "Script",
				"dependsOn": [
					{
						"activity": "Truncate DimBranchZip",
						"dependencyConditions": [
							"Succeeded"
						]
					}
				],
				"policy": {
					"timeout": "7.00:00:00",
					"retry": 0,
					"retryIntervalInSeconds": 30,
					"secureOutput": false,
					"secureInput": false
				},
				"userProperties": [],
				"linkedServiceName": {
					"referenceName": "RDC",
					"type": "LinkedServiceReference"
				},
				"typeProperties": {
					"scripts": [
						{
							"type": "Query",
							"text": "TRUNCATE TABLE EDW.DIM_JOB_STATUS_CATEGORY"
						}
					]
				}
			},
			{
				"name": "Truncate DimInboundKillReason",
				"type": "Script",
				"dependsOn": [
					{
						"activity": "Truncate DimJobStatusCategory",
						"dependencyConditions": [
							"Succeeded"
						]
					}
				],
				"policy": {
					"timeout": "7.00:00:00",
					"retry": 0,
					"retryIntervalInSeconds": 30,
					"secureOutput": false,
					"secureInput": false
				},
				"userProperties": [],
				"linkedServiceName": {
					"referenceName": "RDC",
					"type": "LinkedServiceReference"
				},
				"typeProperties": {
					"scripts": [
						{
							"type": "Query",
							"text": "TRUNCATE TABLE EDW.DIM_INBOUND_KILL_REASON"
						}
					]
				}
			},
			{
				"name": "Truncate DimTimeSlots",
				"type": "Script",
				"dependsOn": [
					{
						"activity": "Truncate DimCallType",
						"dependencyConditions": [
							"Succeeded"
						]
					}
				],
				"policy": {
					"timeout": "0.12:00:00",
					"retry": 0,
					"retryIntervalInSeconds": 30,
					"secureOutput": false,
					"secureInput": false
				},
				"userProperties": [],
				"linkedServiceName": {
					"referenceName": "RDC",
					"type": "LinkedServiceReference"
				},
				"typeProperties": {
					"scripts": [
						{
							"type": "Query",
							"text": "TRUNCATE TABLE EDW.DIM_TIME_SLOTS"
						}
					],
					"scriptBlockExecutionTimeout": "02:00:00"
				}
			},
			{
				"name": "Truncate DimPhones",
				"type": "Script",
				"dependsOn": [
					{
						"activity": "Truncate DimInboundKillReason",
						"dependencyConditions": [
							"Succeeded"
						]
					}
				],
				"policy": {
					"timeout": "7.00:00:00",
					"retry": 0,
					"retryIntervalInSeconds": 30,
					"secureOutput": false,
					"secureInput": false
				},
				"userProperties": [],
				"linkedServiceName": {
					"referenceName": "RDC",
					"type": "LinkedServiceReference"
				},
				"typeProperties": {
					"scripts": [
						{
							"type": "Query",
							"text": "TRUNCATE TABLE EDW.DIM_PHONES"
						}
					]
				}
			},
			{
				"name": "Truncate DimAlternatePhones",
				"type": "Script",
				"dependsOn": [
					{
						"activity": "Truncate DimPhones",
						"dependencyConditions": [
							"Succeeded"
						]
					}
				],
				"policy": {
					"timeout": "7.00:00:00",
					"retry": 0,
					"retryIntervalInSeconds": 30,
					"secureOutput": false,
					"secureInput": false
				},
				"userProperties": [],
				"linkedServiceName": {
					"referenceName": "RDC",
					"type": "LinkedServiceReference"
				},
				"typeProperties": {
					"scripts": [
						{
							"type": "Query",
							"text": "TRUNCATE TABLE EDW.DIM_ALTERNATE_PHONES"
						}
					]
				}
			},
			{
				"name": "Truncate ReportingMarket",
				"type": "Script",
				"dependsOn": [
					{
						"activity": "Truncate DimJobPermitType",
						"dependencyConditions": [
							"Succeeded"
						]
					}
				],
				"policy": {
					"timeout": "7.00:00:00",
					"retry": 0,
					"retryIntervalInSeconds": 30,
					"secureOutput": false,
					"secureInput": false
				},
				"userProperties": [],
				"linkedServiceName": {
					"referenceName": "RDC",
					"type": "LinkedServiceReference"
				},
				"typeProperties": {
					"scripts": [
						{
							"type": "Query",
							"text": "TRUNCATE TABLE [EDW].[DIM_REPORTING_MARKET]"
						}
					]
				}
			},
			{
				"name": "Truncate DimPunchList",
				"type": "Script",
				"dependsOn": [],
				"policy": {
					"timeout": "7.00:00:00",
					"retry": 0,
					"retryIntervalInSeconds": 30,
					"secureOutput": false,
					"secureInput": false
				},
				"userProperties": [],
				"linkedServiceName": {
					"referenceName": "RDC",
					"type": "LinkedServiceReference"
				},
				"typeProperties": {
					"scripts": [
						{
							"type": "Query",
							"text": "TRUNCATE TABLE EDW.DIM_PUNCH_LIST"
						}
					]
				}
			},
			{
				"name": "Truncate Dimplanitem",
				"type": "Script",
				"dependsOn": [
					{
						"activity": "Truncate DimHOAStatus",
						"dependencyConditions": [
							"Succeeded"
						]
					}
				],
				"policy": {
					"timeout": "7.00:00:00",
					"retry": 0,
					"retryIntervalInSeconds": 30,
					"secureOutput": false,
					"secureInput": false
				},
				"userProperties": [],
				"linkedServiceName": {
					"referenceName": "RDC",
					"type": "LinkedServiceReference"
				},
				"typeProperties": {
					"scripts": [
						{
							"type": "Query",
							"text": "TRUNCATE TABLE EDW.DIM_PLANITEM"
						}
					]
				}
			},
			{
				"name": "Truncate Dimprojects",
				"type": "Script",
				"dependsOn": [
					{
						"activity": "Truncate Dimplanitem",
						"dependencyConditions": [
							"Succeeded"
						]
					}
				],
				"policy": {
					"timeout": "7.00:00:00",
					"retry": 0,
					"retryIntervalInSeconds": 30,
					"secureOutput": false,
					"secureInput": false
				},
				"userProperties": [],
				"linkedServiceName": {
					"referenceName": "RDC",
					"type": "LinkedServiceReference"
				},
				"typeProperties": {
					"scripts": [
						{
							"type": "Query",
							"text": "TRUNCATE TABLE EDW.DIM_PROJECTS"
						}
					]
				}
			},
			{
				"name": "Truncate DimSalesType",
				"type": "Script",
				"dependsOn": [
					{
						"activity": "Truncate DimJobStatus",
						"dependencyConditions": [
							"Succeeded"
						]
					}
				],
				"policy": {
					"timeout": "7.00:00:00",
					"retry": 0,
					"retryIntervalInSeconds": 30,
					"secureOutput": false,
					"secureInput": false
				},
				"userProperties": [],
				"linkedServiceName": {
					"referenceName": "RDC",
					"type": "LinkedServiceReference"
				},
				"typeProperties": {
					"scripts": [
						{
							"type": "Query",
							"text": "TRUNCATE TABLE EDW.DIM_SALE_TYPES"
						}
					]
				}
			},
			{
				"name": "Truncate DimEmployeJobType",
				"type": "Script",
				"dependsOn": [
					{
						"activity": "Truncate DimEmployee",
						"dependencyConditions": [
							"Succeeded"
						]
					}
				],
				"policy": {
					"timeout": "7.00:00:00",
					"retry": 0,
					"retryIntervalInSeconds": 30,
					"secureOutput": false,
					"secureInput": false
				},
				"userProperties": [],
				"linkedServiceName": {
					"referenceName": "RDC",
					"type": "LinkedServiceReference"
				},
				"typeProperties": {
					"scripts": [
						{
							"type": "Query",
							"text": "TRUNCATE TABLE EDW.DIM_EMPLOYEE_JOB_TYPE"
						}
					]
				}
			}
		],
		"folder": {
			"name": "ODS_to_EDW/DIMENSIONS/LP"
		},
		"annotations": [],
		"lastPublishTime": "2026-01-12T14:35:05Z"
	},
	"type": "Microsoft.Synapse/workspaces/pipelines"
}