{
	"name": "EDW_DIM_HR_EMPLOYEE_SUB_LOCATION",
	"properties": {
		"annotations": [],
		"type": "SqlPoolTable",
		"schema": [
			{
				"name": "SubLocation_PK",
				"type": "int",
				"precision": 10
			},
			{
				"name": "Division",
				"type": "nvarchar"
			},
			{
				"name": "SubLocation",
				"type": "nvarchar"
			},
			{
				"name": "PayrollCompanyCode",
				"type": "nvarchar"
			},
			{
				"name": "PayrollCompanyName",
				"type": "nvarchar"
			},
			{
				"name": "ACUID",
				"type": "nvarchar"
			},
			{
				"name": "ACUBranch",
				"type": "nvarchar"
			},
			{
				"name": "Market",
				"type": "nvarchar"
			},
			{
				"name": "RecordCreatedDate",
				"type": "date"
			},
			{
				"name": "RecordUpdatedDate",
				"type": "date"
			}
		],
		"typeProperties": {
			"schema": "EDW",
			"table": "DIM_HR_EMPLOYEE_SUB_LOCATION"
		},
		"sqlPool": {
			"referenceName": "rdc_sqlpool_prod",
			"type": "SqlPoolReference"
		}
	},
	"type": "Microsoft.Synapse/workspaces/datasets"
}